TFRE/QICD.cpython-310-darwin.so
TFRE/TFRE.py
TFRE/__init__.py
TFRE-0.0.0.1.dist-info/LICENSE
TFRE-0.0.0.1.dist-info/METADATA
TFRE-0.0.0.1.dist-info/WHEEL
TFRE-0.0.0.1.dist-info/top_level.txt
TFRE-0.0.0.1.dist-info/RECORD
