Metadata-Version: 2.1
Name: TFRE
Version: 0.0.0.1
Summary: A Tuning-Free Robust and Efficient Approach to High-dimensional Regression
Home-page: https://github.com/yunanwu123/TFRE_python
Author: Yunan Wu, Lan Wang
Author-email: yunan.wu@utdallas.edu, lanwang@mbs.miami.edu
Maintainer: Yunan Wu
Maintainer-email: yunan.wu@utdallas.edu
License: MIT license
Keywords: TFRE,high dimensional analysis
Classifier: Intended Audience :: Developers
Classifier: License :: OSI Approved :: MIT License
Classifier: Natural Language :: English
Classifier: Programming Language :: Python
Classifier: Operating System :: OS Independent
Requires-Python: >=3.10
License-File: LICENSE
Requires-Dist: pybind11 >=2.2
Requires-Dist: numpy >=1.10
Requires-Dist: matplotlib
